ffiec_data_collector/__init__.py
ffiec_data_collector/downloader.py
ffiec_data_collector/thumbprint.py
ffiec_data_collector-2.0.0rc2.dist-info/licenses/LICENSE
ffiec_data_collector-2.0.0rc2.dist-info/METADATA
ffiec_data_collector-2.0.0rc2.dist-info/WHEEL
ffiec_data_collector-2.0.0rc2.dist-info/entry_points.txt
ffiec_data_collector-2.0.0rc2.dist-info/top_level.txt
ffiec_data_collector-2.0.0rc2.dist-info/RECORD
