Metadata-Version: 2.4
Name: ffiec-data-collector
Version: 2.0.0rc2
Summary: Lightweight Python library for collecting bulk FFIEC CDR data
Home-page: https://github.com/call-report/ffiec-data-collector
Author: Michael
Author-email: Michael <michael@civicforge.solutions>
License: MPL-2.0
Project-URL: Homepage, https://github.com/call-report/ffiec-data-collector
Project-URL: Documentation, https://ffiec-data-collector.readthedocs.io
Project-URL: Repository, https://github.com/call-report/ffiec-data-collector
Project-URL: Issues, https://github.com/call-report/ffiec-data-collector/issues
Keywords: ffiec,banking,financial,data,cdr,ubpr
Classifier: Development Status :: 4 - Beta
Classifier: Intended Audience :: Developers
Classifier: Intended Audience :: Financial and Insurance Industry
Classifier: Topic :: Office/Business :: Financial
Classifier: Programming Language :: Python :: 3
Classifier: Programming Language :: Python :: 3.10
Classifier: Programming Language :: Python :: 3.11
Classifier: Programming Language :: Python :: 3.12
Classifier: Programming Language :: Python :: 3.13
Requires-Python: >=3.10
License-File: LICENSE
Requires-Dist: requests>=2.28.0
Requires-Dist: python-dateutil>=2.8.0
Provides-Extra: dev
Requires-Dist: pytest>=7.0.0; extra == "dev"
Requires-Dist: pytest-cov>=4.0.0; extra == "dev"
Requires-Dist: black>=22.0.0; extra == "dev"
Requires-Dist: flake8>=5.0.0; extra == "dev"
Requires-Dist: mypy>=0.990; extra == "dev"
Requires-Dist: types-requests>=2.25.0; extra == "dev"
Requires-Dist: jupyter>=1.0.0; extra == "dev"
Requires-Dist: notebook>=6.5.0; extra == "dev"
Requires-Dist: build>=0.10.0; extra == "dev"
Requires-Dist: twine>=4.0.0; extra == "dev"
Requires-Dist: ipykernel>=6.30.1; extra == "dev"
Requires-Dist: uv>=0.8.8; extra == "dev"
Provides-Extra: docs
Requires-Dist: sphinx>=5.0.0; extra == "docs"
Requires-Dist: sphinx-rtd-theme>=1.2.0; extra == "docs"
Requires-Dist: sphinx-autodoc-typehints>=1.19.0; extra == "docs"
Requires-Dist: myst-parser>=0.18.0; extra == "docs"
Requires-Dist: nbsphinx>=0.8.0; extra == "docs"
Provides-Extra: validation
Requires-Dist: jsonschema>=4.0.0; extra == "validation"
Dynamic: author
Dynamic: home-page
Dynamic: license-file
Dynamic: requires-python
